xontrib/mpl.py
xontrib/mplhooks.py
xontrib_mpl-0.0.2.dist-info/LICENSE
xontrib_mpl-0.0.2.dist-info/WHEEL
xontrib_mpl-0.0.2.dist-info/METADATA
xontrib_mpl-0.0.2.dist-info/RECORD
