Metadata-Version: 2.1
Name: xontrib-mpl
Version: 0.0.2
Summary: Matplotlib hooks for xonsh, including the new 'mpl' alias that displays the current figure on the screen
Home-page: https://github.com/xonsh/xontrib-mpl
License: MIT
Keywords: xontrib,xonsh
Author: Noortheen Raa
Author-email: jnoortheen@gmail.com
Requires-Python: >=3.7
Classifier: Intended Audience :: Developers
Classifier: License :: OSI Approved :: MIT License
Classifier: Natural Language :: English
Classifier: Operating System :: OS Independent
Classifier: Programming Language :: Python
Classifier: Programming Language :: Python :: 3
Classifier: Programming Language :: Python :: 3.10
Classifier: Programming Language :: Python :: 3.6
Classifier: Programming Language :: Python :: 3.7
Classifier: Programming Language :: Python :: 3.8
Classifier: Programming Language :: Python :: 3.9
Classifier: Topic :: System :: Shells
Classifier: Topic :: System :: System Shells
Classifier: Topic :: Terminals
Requires-Dist: xonsh (>=0.12)
Project-URL: Code, https://github.com/xonsh/xontrib-mpl
Project-URL: Documentation, https://github.com/xonsh/xontrib-mpl/blob/master/README.md
Project-URL: Issue tracker, https://github.com/xonsh/xontrib-mpl/issues
Project-URL: Repository, https://github.com/xonsh/xontrib-mpl
